pywa/__init__.py
pywa/api.py
pywa/client.py
pywa/errors.py
pywa/filters.py
pywa/handlers.py
pywa/server.py
pywa/utils.py
pywa/types/__init__.py
pywa/types/base_update.py
pywa/types/callback.py
pywa/types/chat_opened.py
pywa/types/flows.py
pywa/types/media.py
pywa/types/message.py
pywa/types/message_status.py
pywa/types/others.py
pywa/types/template.py
pywa_async/__init__.py
pywa_async/api.py
pywa_async/client.py
pywa_async/errors.py
pywa_async/filters.py
pywa_async/handlers.py
pywa_async/utils.py
pywa_async/types/__init__.py
pywa_async/types/base_update.py
pywa_async/types/callback.py
pywa_async/types/chat_opened.py
pywa_async/types/flows.py
pywa_async/types/media.py
pywa_async/types/message.py
pywa_async/types/message_status.py
pywa_async/types/others.py
pywa_async/types/template.py
pywaai/__init__.py
pywaai/ai_utils.py
pywaai/conversation_db.py
pywaai/models.py
pywaai-0.0.18.dist-info/LICENSE
pywaai-0.0.18.dist-info/METADATA
pywaai-0.0.18.dist-info/WHEEL
pywaai-0.0.18.dist-info/top_level.txt
pywaai-0.0.18.dist-info/RECORD
